ANIDSC/__init__.py
ANIDSC/templates.py
ANIDSC/utils.py
ANIDSC/adversarial_attacks/__init__.py
ANIDSC/adversarial_attacks/liuer_mihou.py
ANIDSC/base_files/__init__.py
ANIDSC/base_files/evaluator.py
ANIDSC/base_files/feature_extractor.py
ANIDSC/base_files/model.py
ANIDSC/base_files/normalizer.py
ANIDSC/base_files/pipeline.py
ANIDSC/base_files/save_mixin.py
ANIDSC/cdd_frameworks/__init__.py
ANIDSC/cdd_frameworks/arcus.py
ANIDSC/cdd_frameworks/drift_sense.py
ANIDSC/data_source/__init__.py
ANIDSC/data_source/live_sources.py
ANIDSC/data_source/offline_sources.py
ANIDSC/evaluations/__init__.py
ANIDSC/evaluations/od_metrics.py
ANIDSC/evaluations/summarizer.py
ANIDSC/feature_extractors/__init__.py
ANIDSC/feature_extractors/after_image.py
ANIDSC/feature_extractors/frequency.py
ANIDSC/feature_extractors/pyflowmeter.py
ANIDSC/feature_extractors/synthetic_graph_features.py
ANIDSC/models/__init__.py
ANIDSC/models/autoencoder.py
ANIDSC/models/boxplot.py
ANIDSC/models/gnnids.py
ANIDSC/models/goad.py
ANIDSC/models/icl.py
ANIDSC/models/kitsune.py
ANIDSC/models/kitsune_torch.py
ANIDSC/models/slad.py
ANIDSC/normalizer/__init__.py
ANIDSC/normalizer/t_digest.py
ANIDSC-0.1.0.dist-info/LICENSE
ANIDSC-0.1.0.dist-info/METADATA
ANIDSC-0.1.0.dist-info/WHEEL
ANIDSC-0.1.0.dist-info/top_level.txt
ANIDSC-0.1.0.dist-info/RECORD
