Metadata-Version: 2.1
Name: ANIDSC
Version: 0.1.0
Summary: Adversarial testing framework for NIDS
Author-email: Ke He <kh695640204@gmail.com>
Project-URL: Homepage, https://github.com/kihy/ANIDSC
Project-URL: Issues, https://github.com/kihy/ANIDSC/issues
Classifier: Programming Language :: Python :: 3
Classifier: License :: OSI Approved :: GNU General Public License (GPL)
Classifier: Operating System :: OS Independent
Classifier: Development Status :: 1 - Planning
Requires-Python: >=3.10
License-File: LICENSE
